Metadata-Version: 2.1
Name: composable-logs-snapshot
Version: 0.0.12.dev1677938878
Summary: UNKNOWN
Home-page: https://github.com/composable-logs/composable-logs
Author: Matias Dahl
Author-email: matias.dahl@iki.fi
License: MIT
Platform: UNKNOWN
Classifier: License :: OSI Approved :: MIT License
Requires-Dist: fastapi (==0.91.0)
Requires-Dist: fastcore (==1.4.3)
Requires-Dist: ghapi (==0.1.19)
Requires-Dist: jsonschema[format-nongpl] (==4.17.3)
Requires-Dist: jupyter-client (==7.4.9)
Requires-Dist: jupytext (==1.14.4)
Requires-Dist: mlflow-skinny (==2.1.1)
Requires-Dist: notebook (==6.5.2)
Requires-Dist: opentelemetry-api (==1.15.0)
Requires-Dist: opentelemetry-exporter-otlp (==1.15.0)
Requires-Dist: opentelemetry-sdk (==1.15.0)
Requires-Dist: papermill (==2.4.0)
Requires-Dist: pydantic (==1.10.4)
Requires-Dist: pyftpdlib (==1.5.7)
Requires-Dist: python-dateutil (==2.8.2)
Requires-Dist: ray[default] (==2.3.0)
Requires-Dist: requests (==2.27.1)
Requires-Dist: types-requests (==2.28.11.14)
Requires-Dist: types-urllib3 (==1.26.25.7)
Requires-Dist: uvicorn (==0.20.0)
